odoo/addons/l10n_br_fiscal_closing/README.rst
odoo/addons/l10n_br_fiscal_closing/__init__.py
odoo/addons/l10n_br_fiscal_closing/__manifest__.py
odoo/addons/l10n_br_fiscal_closing/i18n/l10n_br_fiscal_closing.pot
odoo/addons/l10n_br_fiscal_closing/i18n/pt_BR.po
odoo/addons/l10n_br_fiscal_closing/models/__init__.py
odoo/addons/l10n_br_fiscal_closing/models/closing.py
odoo/addons/l10n_br_fiscal_closing/models/document.py
odoo/addons/l10n_br_fiscal_closing/readme/CONFIGURE.rst
odoo/addons/l10n_br_fiscal_closing/readme/CONTRIBUTORS.rst
odoo/addons/l10n_br_fiscal_closing/readme/CREDITS.rst
odoo/addons/l10n_br_fiscal_closing/readme/DESCRIPTION.rst
odoo/addons/l10n_br_fiscal_closing/readme/HISTORY.rst
odoo/addons/l10n_br_fiscal_closing/readme/INSTALL.rst
odoo/addons/l10n_br_fiscal_closing/readme/ROADMAP.rst
odoo/addons/l10n_br_fiscal_closing/readme/USAGE.rst
odoo/addons/l10n_br_fiscal_closing/security/ir.model.access.csv
odoo/addons/l10n_br_fiscal_closing/static/description/icon.png
odoo/addons/l10n_br_fiscal_closing/static/description/index.html
odoo/addons/l10n_br_fiscal_closing/tests/__init__.py
odoo/addons/l10n_br_fiscal_closing/tests/test_fiscal_closing.py
odoo/addons/l10n_br_fiscal_closing/views/closing.xml
odoo14_addon_l10n_br_fiscal_closing-14.0.2.1.1.dist-info/METADATA
odoo14_addon_l10n_br_fiscal_closing-14.0.2.1.1.dist-info/WHEEL
odoo14_addon_l10n_br_fiscal_closing-14.0.2.1.1.dist-info/top_level.txt
odoo14_addon_l10n_br_fiscal_closing-14.0.2.1.1.dist-info/RECORD
