Metadata-Version: 2.1
Name: odoo14-addon-l10n_br_fiscal_closing
Version: 14.0.2.1.1
Summary: Period fiscal closing
Home-page: https://github.com/OCA/l10n-brazil
Author: KMEE,Odoo Community Association (OCA)
Author-email: support@odoo-community.org
License: AGPL-3
Classifier: Programming Language :: Python
Classifier: Framework :: Odoo
Classifier: Framework :: Odoo :: 14.0
Classifier: License :: OSI Approved :: GNU Affero General Public License v3
Requires-Python: >=3.6
Requires-Dist: erpbrasil.base
Requires-Dist: odoo14-addon-l10n-br-fiscal-edi
Requires-Dist: odoo<14.1dev,>=14.0a
